{"scancompletedon":"2016-10-27T16:43:36.89056","targetlist":"Sched1","id":"30f69eb9-9210-4fb8-9378-d598279575d9","type":"ScanMetadata","scanname":"20161027-1638","hostcount":1,"failedhosts":0,"processcount":27,"modulecount":437,"drivercount":134,"memorycount":3,"autostartcount":405,"accountcount":6,"hookcount":40,"totalobjectcount":1052,"compromisedhosts":1,"compromisedaccounts":1,"compromisedobjects":5,"scanid":"30f69eb9-9210-4fb8-9378-d598279575d9","bad":5,"suspicious":0,"unknown":1,"lowrisk":32,"good":968}
{"scancompletedon":"2016-10-27T17:32:25.429285","targetlist":"VMTestNet","id":"62b6a344-6377-4b68-83f1-90f36c3edcce","type":"ScanMetadata","scanname":"20161027-1724","hostcount":3,"failedhosts":0,"processcount":57,"modulecount":1020,"drivercount":308,"memorycount":3,"autostartcount":904,"accountcount":15,"hookcount":198,"totalobjectcount":2505,"compromisedhosts":1,"compromisedaccounts":1,"compromisedobjects":6,"scanid":"62b6a344-6377-4b68-83f1-90f36c3edcce","bad":6,"suspicious":1,"unknown":0,"lowrisk":465,"good":1820}
{"scancompletedon":"2016-10-27T16:40:35.97775","targetlist":"VMTestNet","id":"bc7ad3e3-1e6e-4136-8b86-d17f4885e67e","type":"ScanMetadata","scanname":"20161027-1631","hostcount":3,"failedhosts":0,"processcount":58,"modulecount":1019,"drivercount":308,"memorycount":3,"autostartcount":904,"accountcount":16,"hookcount":53,"totalobjectcount":2361,"compromisedhosts":1,"compromisedaccounts":1,"compromisedobjects":6,"scanid":"bc7ad3e3-1e6e-4136-8b86-d17f4885e67e","bad":6,"suspicious":1,"unknown":0,"lowrisk":466,"good":1819}
{"scancompletedon":"2016-10-27T18:54:06.541894","targetlist":"VMTestNet","id":"2a31320b-6b89-4a9e-9000-05a7a3adb375","type":"ScanMetadata","scanname":"20161027-1843","hostcount":4,"failedhosts":0,"processcount":152,"modulecount":2495,"drivercount":505,"memorycount":3,"autostartcount":1546,"accountcount":22,"hookcount":373,"totalobjectcount":5096,"compromisedhosts":1,"compromisedaccounts":1,"compromisedobjects":6,"scanid":"2a31320b-6b89-4a9e-9000-05a7a3adb375","bad":6,"suspicious":7,"unknown":2,"lowrisk":2768,"good":1918}
{"scancompletedon":"2016-10-27T16:49:21.951786","targetlist":"LocalTest","id":"e2d07154-0420-4a7d-a958-21245cce7fe6","type":"ScanMetadata","scanname":"20161027-1645","hostcount":1,"failedhosts":0,"processcount":87,"modulecount":1210,"drivercount":201,"memorycount":0,"autostartcount":645,"accountcount":9,"hookcount":72,"totalobjectcount":2224,"compromisedhosts":0,"compromisedaccounts":0,"compromisedobjects":0,"scanid":"e2d07154-0420-4a7d-a958-21245cce7fe6","bad":0,"suspicious":6,"unknown":1,"lowrisk":2106,"good":30}
{"scancompletedon":"2016-10-28T16:49:08.771961","targetlist":"LocalTest","id":"4474f5ed-6ea0-4487-85cf-452f1f41ce7a","type":"ScanMetadata","scanname":"20161028-1645","hostcount":1,"failedhosts":0,"processcount":81,"modulecount":1220,"drivercount":195,"memorycount":0,"autostartcount":645,"accountcount":9,"hookcount":228,"totalobjectcount":2378,"compromisedhosts":0,"compromisedaccounts":0,"compromisedobjects":0,"scanid":"4474f5ed-6ea0-4487-85cf-452f1f41ce7a","bad":0,"suspicious":5,"unknown":32,"lowrisk":2072,"good":32}
{"scancompletedon":"2016-10-27T22:34:02.398884","targetlist":"VMTestNet","id":"5ab37181-50ab-4b8f-bfd3-eb5920eda54a","type":"ScanMetadata","scanname":"20161027-2220","hostcount":4,"failedhosts":0,"processcount":151,"modulecount":2469,"drivercount":505,"memorycount":3,"autostartcount":1546,"accountcount":22,"hookcount":466,"totalobjectcount":5162,"compromisedhosts":1,"compromisedaccounts":1,"compromisedobjects":6,"scanid":"5ab37181-50ab-4b8f-bfd3-eb5920eda54a","bad":6,"suspicious":7,"unknown":2,"lowrisk":2733,"good":1926}
{"scancompletedon":"2016-10-27T16:43:53.751598","targetlist":"Sched2","id":"098609ed-01d2-4cf6-9b67-e23c75279e0e","type":"ScanMetadata","scanname":"20161027-1636","hostcount":1,"failedhosts":0,"processcount":21,"modulecount":357,"drivercount":135,"memorycount":0,"autostartcount":354,"accountcount":6,"hookcount":38,"totalobjectcount":911,"compromisedhosts":0,"compromisedaccounts":0,"compromisedobjects":0,"scanid":"098609ed-01d2-4cf6-9b67-e23c75279e0e","bad":0,"suspicious":1,"unknown":0,"lowrisk":200,"good":666}
{"scancompletedon":"2016-10-27T16:35:42.186494","targetlist":"LocalTest","id":"11b37522-a402-46b9-83d2-5debed2c2ea7","type":"ScanMetadata","scanname":"20161027-1629","hostcount":1,"failedhosts":0,"processcount":86,"modulecount":1202,"drivercount":201,"memorycount":0,"autostartcount":645,"accountcount":9,"hookcount":36,"totalobjectcount":2179,"compromisedhosts":0,"compromisedaccounts":0,"compromisedobjects":0,"scanid":"11b37522-a402-46b9-83d2-5debed2c2ea7","bad":0,"suspicious":6,"unknown":1,"lowrisk":2097,"good":30}
{"scancompletedon":"2016-10-27T22:55:37.709276","targetlist":"VMTestNet","id":"0f73292f-5dc4-48cf-880b-a4ae1d31b0a6","type":"ScanMetadata","scanname":"20161027-2236","hostcount":1,"failedhosts":5,"processcount":89,"modulecount":1238,"drivercount":201,"memorycount":0,"autostartcount":645,"accountcount":9,"hookcount":190,"totalobjectcount":2372,"compromisedhosts":0,"compromisedaccounts":0,"compromisedobjects":0,"scanid":"0f73292f-5dc4-48cf-880b-a4ae1d31b0a6","bad":0,"suspicious":6,"unknown":2,"lowrisk":2133,"good":32}
{"scancompletedon":"2016-10-27T16:47:59.327718","targetlist":"Sched3","id":"d70a9f54-5bc0-4e8e-b0dd-78c5585f3e31","type":"ScanMetadata","scanname":"20161027-1640","hostcount":3,"failedhosts":0,"processcount":57,"modulecount":1019,"drivercount":308,"memorycount":3,"autostartcount":904,"accountcount":16,"hookcount":145,"totalobjectcount":2452,"compromisedhosts":1,"compromisedaccounts":1,"compromisedobjects":5,"scanid":"d70a9f54-5bc0-4e8e-b0dd-78c5585f3e31","bad":5,"suspicious":1,"unknown":1,"lowrisk":465,"good":1819}
{"scancompletedon":"2016-10-28T16:43:37.234406","targetlist":"Sched3","id":"a1a140f3-9492-4f41-9059-2bd727d2a1e5","type":"ScanMetadata","scanname":"20161028-1640","hostcount":0,"failedhosts":3,"processcount":0,"modulecount":0,"drivercount":0,"memorycount":0,"autostartcount":0,"accountcount":0,"hookcount":0,"totalobjectcount":0,"compromisedhosts":0,"compromisedaccounts":0,"compromisedobjects":null,"scanid":null,"bad":null,"suspicious":null,"unknown":null,"lowrisk":null,"good":null}
{"scancompletedon":"2016-10-28T16:39:40.844215","targetlist":"Sched2","id":"39740ecd-cc1b-4ad9-872d-f30bbefccb14","type":"ScanMetadata","scanname":"20161028-1636","hostcount":0,"failedhosts":1,"processcount":0,"modulecount":0,"drivercount":0,"memorycount":0,"autostartcount":0,"accountcount":0,"hookcount":0,"totalobjectcount":0,"compromisedhosts":0,"compromisedaccounts":0,"compromisedobjects":null,"scanid":null,"bad":null,"suspicious":null,"unknown":null,"lowrisk":null,"good":null}
{"scancompletedon":"2016-10-28T16:41:30.539006","targetlist":"Sched1","id":"b77d0ec3-c30e-4b15-a665-7f9ec40cce4d","type":"ScanMetadata","scanname":"20161028-1638","hostcount":0,"failedhosts":1,"processcount":0,"modulecount":0,"drivercount":0,"memorycount":0,"autostartcount":0,"accountcount":0,"hookcount":0,"totalobjectcount":0,"compromisedhosts":0,"compromisedaccounts":0,"compromisedobjects":null,"scanid":null,"bad":null,"suspicious":null,"unknown":null,"lowrisk":null,"good":null}
